sag_calc/__init__.py
sag_calc-0.0.1.dist-info/LICENSE.txt
sag_calc-0.0.1.dist-info/METADATA
sag_calc-0.0.1.dist-info/WHEEL
sag_calc-0.0.1.dist-info/top_level.txt
sag_calc-0.0.1.dist-info/RECORD
